main.py
image_mcp-0.1.3.dist-info/licenses/LICENSE
image_mcp-0.1.3.dist-info/METADATA
image_mcp-0.1.3.dist-info/WHEEL
image_mcp-0.1.3.dist-info/entry_points.txt
image_mcp-0.1.3.dist-info/top_level.txt
image_mcp-0.1.3.dist-info/RECORD
