Metadata-Version: 2.4
Name: image-mcp
Version: 0.1.3
Summary: A simple MCP server that loads images from a local path or HTTP/HTTPS URL
Author-email: Abhay Deshpande <a.deshpande012@gmail.com>
Maintainer-email: Abhay Deshpande <a.deshpande012@gmail.com>
License: MIT License
Project-URL: Homepage, https://github.com/abhaybd/Image-MCP
Project-URL: Repository, https://github.com/abhaybd/Image-MCP
Keywords: mcp,model context protocol,image,ai,agent
Classifier: Development Status :: 3 - Alpha
Classifier: Intended Audience :: Developers
Classifier: License :: OSI Approved :: MIT License
Classifier: Operating System :: OS Independent
Classifier: Programming Language :: Python
Classifier: Programming Language :: Python :: 3
Classifier: Programming Language :: Python :: 3 :: Only
Classifier: Programming Language :: Python :: 3.10
Classifier: Programming Language :: Python :: 3.11
Classifier: Programming Language :: Python :: 3.12
Classifier: Topic :: Utilities
Classifier: Topic :: Scientific/Engineering :: Artificial Intelligence
Classifier: Topic :: Scientific/Engineering :: Image Processing
Classifier: Natural Language :: English
Requires-Python: >=3.10
License-File: LICENSE
Requires-Dist: httpx>=0.28.1
Requires-Dist: mcp[cli]>=1.12.4
Requires-Dist: pillow>=11.3.0
Dynamic: license-file
